sipvicious/__init__.py
sipvicious/svcrack.py
sipvicious/svcrash.py
sipvicious/svmap.py
sipvicious/svreport.py
sipvicious/svwar.py
sipvicious/libs/__init__.py
sipvicious/libs/pptable.py
sipvicious/libs/svhelper.py
sipvicious-0.3.4.data/data/man/man1/svcrack.1
sipvicious-0.3.4.data/data/man/man1/svcrash.1
sipvicious-0.3.4.data/data/man/man1/svmap.1
sipvicious-0.3.4.data/data/man/man1/svreport.1
sipvicious-0.3.4.data/data/man/man1/svwar.1
sipvicious-0.3.4.dist-info/LICENSE
sipvicious-0.3.4.dist-info/METADATA
sipvicious-0.3.4.dist-info/WHEEL
sipvicious-0.3.4.dist-info/entry_points.txt
sipvicious-0.3.4.dist-info/top_level.txt
sipvicious-0.3.4.dist-info/RECORD
