Metadata-Version: 2.1
Name: sipvicious
Version: 0.3.4
Summary: SIPVicious suite is a set of tools that can be used to audit SIP based VoIP systems.
Home-page: https://github.com/EnableSecurity/sipvicious
Author: Sandro Gauci <sandro@enablesecurity.com>
Author-email: sandro@enablesecurity.com
License: GPL
Download-URL: https://github.com/EnableSecurity/sipvicious/archive/v0.3.4.zip
Project-URL: Bug Tracker, https://github.com/EnableSecurity/sipvicious/issues
Project-URL: Source Code, https://github.com/EnableSecurity/sipvicious/tree/master
Keywords: telephony sip audit scanner voip
Platform: UNKNOWN
Classifier: Development Status :: 5 - Production/Stable
Classifier: Intended Audience :: System Administrators
Classifier: Intended Audience :: Information Technology
Classifier: Topic :: Internet
Classifier: Topic :: Security
Classifier: Topic :: System :: Networking
Classifier: Topic :: Communications :: Telephony
Classifier: Topic :: Communications :: Internet Phone
Classifier: License :: OSI Approved :: GNU General Public License (GPL)
Classifier: Programming Language :: Python :: 3
Classifier: Operating System :: OS Independent
Requires-Python: >=3.6
